xlms_tools/__init__.py
xlms_tools/depth.py
xlms_tools/main.py
xlms_tools/parsers.py
xlms_tools/printing.py
xlms_tools/score.py
xlms_tools/simulate.py
xlms_tools/visualization.py
xlms_tools-1.0.9.dist-info/LICENSE
xlms_tools-1.0.9.dist-info/METADATA
xlms_tools-1.0.9.dist-info/WHEEL
xlms_tools-1.0.9.dist-info/entry_points.txt
xlms_tools-1.0.9.dist-info/top_level.txt
xlms_tools-1.0.9.dist-info/RECORD
