Metadata-Version: 2.1
Name: xlms-tools
Version: 1.0.9
Summary: xlms-tools is a set of command line tools to apply crosslinking mass spectrometry (XL-MS) data to protein structure models.
Author-email: Topf Lab <karen.manalastas-cantos@cssb-hamburg.de>
Project-URL: Homepage, https://gitlab.com/topf-lab/xlms-tools
Classifier: Programming Language :: Python :: 3
Classifier: License :: OSI Approved :: MIT License
Classifier: Operating System :: POSIX :: Linux
Requires-Python: >=3.7
License-File: LICENSE
Requires-Dist: biopython >=1.78
Requires-Dist: numpy >=1.19.2
Requires-Dist: scipy >=1.5.2
